shivduttchoubey/__init__.py
shivduttchoubey/website.py
shivduttchoubey-0.1.0.dist-info/LICENSE
shivduttchoubey-0.1.0.dist-info/METADATA
shivduttchoubey-0.1.0.dist-info/WHEEL
shivduttchoubey-0.1.0.dist-info/top_level.txt
shivduttchoubey-0.1.0.dist-info/RECORD
