Metadata-Version: 2.1
Name: shivduttchoubey
Version: 0.1.0
Summary: A package to open Shivdutt Choubey's website
Home-page: https://github.com/shivduttchoubey/shivduttchoubey
Author: Shivdutt Choubey
Author-email: your.email@example.com
Classifier: Programming Language :: Python :: 3
Classifier: License :: OSI Approved :: MIT License
Classifier: Operating System :: OS Independent
Requires-Python: >=3.6
License-File: LICENSE
